LICENSE
README.md
setup.py
./simple_cache/__init__.py
./simple_cache/cache.py
./simple_cache/single_redis.py
./tests/__init__.py
./tests/test_cache.py
simple_function_cache.egg-info/PKG-INFO
simple_function_cache.egg-info/SOURCES.txt
simple_function_cache.egg-info/dependency_links.txt
simple_function_cache.egg-info/not-zip-safe
simple_function_cache.egg-info/requires.txt
simple_function_cache.egg-info/top_level.txt